PPtool/__init__.py
PPtool/info.xlsx
PPtool/method.py
PPtool-0.0.5.dist-info/LICENSE
PPtool-0.0.5.dist-info/METADATA
PPtool-0.0.5.dist-info/WHEEL
PPtool-0.0.5.dist-info/top_level.txt
PPtool-0.0.5.dist-info/RECORD
