Metadata-Version: 2.1
Name: PPtool
Version: 0.0.5
Summary: PPtool is a Python third-party package that integrates many convenient methods for using the PPdata package.
Home-page: https://github.com/zemengchuan/PPtool
Author: zemengchuan
Author-email: zemengchuan@gmail.com
License: MIT
Keywords: PPshare,webcrawler,data,PPdata,tool
Classifier: Programming Language :: Python :: 3.7
Classifier: Programming Language :: Python :: 3.8
Classifier: Programming Language :: Python :: 3.9
Classifier: Programming Language :: Python :: 3.10
Classifier: Programming Language :: Python :: 3.11
Classifier: License :: OSI Approved :: MIT License
Classifier: Operating System :: OS Independent
Requires-Python: >=3.7
License-File: LICENSE
Requires-Dist: fuzzywuzzy (>=0.18.0)
Requires-Dist: pandas (>=1.5)
